{
    "id":1,
    "name":"Belle",
    "challenge":1,
    "score":3
}
{
    "id":2,
    "name":"Nic",
    "challenge":1,
    "score":4
}
{
    "id":3,
    "name":"Belle",
    "challenge":1,
    "score":5
}
{
    "id":4,
    "name":"Nic",
    "challenge":1,
    "score":2
}
{
    "id":5,
    "name":"Belle",
    "challenge":2,
    "score":3
}
{
    "id":6,
    "name":"Nic",
    "challenge":2,
    "score":4
}
{
    "id":7,
    "name":"Belle",
    "challenge":2,
    "score":5
}
{
    "id":8,
    "name":"Nic",
    "challenge":2,
    "score":6
}
